fancybbox/__init__.py
fancybbox/fancy_bbox.py
fancybbox-0.0.12.dist-info/LICENSE.txt
fancybbox-0.0.12.dist-info/METADATA
fancybbox-0.0.12.dist-info/WHEEL
fancybbox-0.0.12.dist-info/top_level.txt
fancybbox-0.0.12.dist-info/RECORD
