Metadata-Version: 2.1
Name: fancybbox
Version: 0.0.12
Summary: Fancy Bounding Box - Rectangle for Object Detection
Home-page: https://github.com/Vprashant/fancybbox
Author: Prashant Verma
Author-email: prashant27050@gmail.com
Keywords: python,image processing,bbox,bbox regtangle,fancy rectangle,bounding box
Classifier: Development Status :: 1 - Planning
Classifier: Intended Audience :: Developers
Classifier: Programming Language :: Python :: 3
Classifier: Operating System :: Unix
Classifier: Operating System :: MacOS :: MacOS X
Classifier: Operating System :: Microsoft :: Windows
License-File: LICENSE.txt
Requires-Dist: opencv-python
